tms_django_log/__init__.py
tms_django_log/admin.py
tms_django_log/apps.py
tms_django_log/models.py
tms_django_log/settings.py
tms_django_log/migrations/0001_initial.py
tms_django_log/migrations/__init__.py
tms_django_log-1.0.2.dist-info/METADATA
tms_django_log-1.0.2.dist-info/WHEEL
tms_django_log-1.0.2.dist-info/top_level.txt
tms_django_log-1.0.2.dist-info/RECORD
